LICENSE
MANIFEST.in
README.rst
VERSION
setup.py
osome/__init__.py
osome/path.py
osome/run.py
osome.egg-info/PKG-INFO
osome.egg-info/SOURCES.txt
osome.egg-info/dependency_links.txt
osome.egg-info/top_level.txt
tests/__init__.py
tests/path_test.py
tests/run_test.py