Metadata-Version: 1.1
Name: osome
Version: 0.1.0
Summary: The bucket of python shell helpers, no dependencies, simple API.
Home-page: https://github.com/xando/osome
Author: Sebastian Pawluś
Author-email: sebastian.pawlus@gmail.com
License: Copyright (c) 2012, Sebastian Pawluś.
